MANIFEST.in
README.rst
agen.py
setup.cfg
setup.py
agen.egg-info/PKG-INFO
agen.egg-info/SOURCES.txt
agen.egg-info/dependency_links.txt
agen.egg-info/entry_points.txt
agen.egg-info/not-zip-safe
agen.egg-info/pbr.json
agen.egg-info/requires.txt
agen.egg-info/top_level.txt
docs/Makefile
tests/test_all.py
tests/context/demo.json
tests/context/demo.yaml
tests/templates/single.txt
tests/templates/directory/__init__.py
tests/templates/directory/{{name}}.py
tests/templates/repo/README.md
tests/templates/repo/agen.json
tests/templates/repo/{{name}}/__init__.py
tests/templates/repo/{{name}}/{{name}}.py