Metadata-Version: 1.0
Name: agen
Version: 0.1.1
Summary: A very simple code generator.
Home-page: https://github.com/yufeiminds/agen
Author: Yufei Li
Author-email: yufeiminds@163.com
License: MIT
Keywords: agen
Platform: UNKNOWN
Classifier: Development Status :: 2 - Pre-Alpha
Classifier: Intended Audience :: Developers
Classifier: License :: OSI Approved :: MIT License
Classifier: Natural Language :: English
Classifier: Programming Language :: Python :: 2
Classifier: Programming Language :: Python :: 2.6
Classifier: Programming Language :: Python :: 2.7
Classifier: Programming Language :: Python :: 3
Classifier: Programming Language :: Python :: 3.3
Classifier: Programming Language :: Python :: 3.4
Classifier: Programming Language :: Python :: 3.5
